ivers/__init__.py
ivers/allforfree.py
ivers/leaky.py
ivers/scaffold.py
ivers/stratify.py
ivers/temporal copy.py
ivers/temporal.py
test/__init__.py
test/test_cv.py
test/test_scaffold.py
test/test_stratify.py
test/test_stratify_cv.py
test/test_temporal.py
test/test_temporal_allforfree.py
test/test_temporal_leaky.py
ivers-0.3.1.dist-info/LICENSE
ivers-0.3.1.dist-info/METADATA
ivers-0.3.1.dist-info/WHEEL
ivers-0.3.1.dist-info/top_level.txt
ivers-0.3.1.dist-info/RECORD
