Metadata-Version: 2.2
Name: ivers
Version: 0.3.1
Summary: Python package for generating realistic training and testing splits for machine learning in cheminformatics and bioinformatics
Home-page: http://github.com/iversohlsson/ivers
Author: Philip Ivers Ohlsson
Author-email: philip.iversohlsson@gmail.com
Classifier: Development Status :: 3 - Alpha
Classifier: Intended Audience :: Developers
Classifier: Programming Language :: Python :: 3
Classifier: Programming Language :: Python :: 3.7
Classifier: Programming Language :: Python :: 3.8
Classifier: Programming Language :: Python :: 3.9
Classifier: Programming Language :: Python :: 3.10
Classifier: License :: OSI Approved :: MIT License
Classifier: Operating System :: OS Independent
License-File: LICENSE
Requires-Dist: pandas
Requires-Dist: scikit-learnnploggingrdkit
Dynamic: author
Dynamic: author-email
Dynamic: classifier
Dynamic: description
Dynamic: description-content-type
Dynamic: home-page
Dynamic: requires-dist
Dynamic: summary
